flask_redoc/__init__.py
flask_redoc/version.py
flask_redoc/static/js/redoc.standalone.js
flask_redoc/templates/docs.html
flask_redoc-0.2.1.dist-info/LICENSE
flask_redoc-0.2.1.dist-info/METADATA
flask_redoc-0.2.1.dist-info/WHEEL
flask_redoc-0.2.1.dist-info/top_level.txt
flask_redoc-0.2.1.dist-info/RECORD
