Metadata-Version: 2.1
Name: flask-redoc
Version: 0.2.1
Summary: UNKNOWN
Home-page: https://github.com/mzaglia/flask-redoc
Author: Matheus C. Zaglia
Author-email: mzaglia@gmail.com
License: MIT
Platform: any
Classifier: Development Status :: 3 - Alpha
Classifier: Environment :: Web Environment
Classifier: License :: OSI Approved :: MIT License
Classifier: Operating System :: OS Independent
Classifier: Programming Language :: Python :: 3.7
Classifier: Topic :: Internet :: WWW/HTTP :: Dynamic Content
Classifier: Topic :: Software Development :: Libraries :: Python Modules
Provides-Extra: docs
Provides-Extra: tests
Provides-Extra: all
